django_fieldsets_inlines_jat-0.1.dist-info/licenses/LICENSE
fieldsets_with_inlines/__init__.py
fieldsets_with_inlines/mixins.py
fieldsets_with_inlines/templates/fieldsets_with_inlines/change_form.html
fieldsets_with_inlines/templates/fieldsets_with_inlines/fieldset.html
django_fieldsets_inlines_jat-0.1.dist-info/METADATA
django_fieldsets_inlines_jat-0.1.dist-info/WHEEL
django_fieldsets_inlines_jat-0.1.dist-info/top_level.txt
django_fieldsets_inlines_jat-0.1.dist-info/RECORD
