Metadata-Version: 2.4
Name: django_fieldsets_inlines-jat
Version: 0.1
Summary: Mixin inlines and fieldsets in Django admin.
Home-page: https://github.com/javware/django-fieldsets-inlines-jat
Author: Jat
Author-email: jat@gmail.com
License: MIT
Classifier: Programming Language :: Python :: 3
Classifier: License :: OSI Approved :: MIT License
Classifier: Operating System :: OS Independent
Classifier: Framework :: Django
Classifier: Framework :: Django :: 3.0
Classifier: Intended Audience :: Developers
Requires-Python: >=3.4
License-File: LICENSE
Dynamic: author
Dynamic: author-email
Dynamic: classifier
Dynamic: description
Dynamic: description-content-type
Dynamic: home-page
Dynamic: license
Dynamic: license-file
Dynamic: requires-python
Dynamic: summary
